{
    "products": [
        {
            "name": "Шоколад",
            "price": 50,
            "available": true,
            "weight": 100
        },
        {
            "name": "Кофе",
            "price": 100,
            "available": false,
            "weight": 250
        },
        {
            "name": "Чай",
            "price": 70,
            "available": true,
            "weight": 50
        },
        {
            "name": "ffa",
            "price": 213,
            "weight": 123,
            "available": true
        },
        {
            "name": "awfaw",
            "price": 21321,
            "weight": 132,
            "available": true
        }
    ]
}